{"acronym": null, "badges": [], "created_at": "2014-07-11T10:28:09.579000", "deleted": null, "description": "Les 1000 références les plus empruntées en 2014 au sein des\nbibliothèques municipales de la ville de Paris. \n\n**Attention, les nombres d'exemplaires ne sont pas indiqués, mais jouent\nun rôle important. Ainsi les titres jeunesse sont présents en nombre\nd'exemplaires très élevé, ce qui explique la prédominance de ces titres\ndans la liste.**\n\nLa mise de ce jeu de données est semestrielle.\n\nEn pièce jointe, vous trouverez le même fichier au format xls contenant\nles liens vers les oeuvres.", "extras": {"datagouv_ckan_id": "30e37457-4c18-4c1a-a056-6b01f392ce2d", "datagouv_ckan_last_sync": "2014-09-16T09:29:11.257000", "remote_url": "http://opendata.paris.fr/explore/dataset/les-titres-les-plus-pretes/"}, "frequency": "unknown", "frequency_date": null, "id": "53c26bbba3a7292df9d3196e", "last_modified": "2015-10-13T09:33:17.609000", "last_update": "2014-07-13T13:21:31.796000", "license": "odc-odbl", "metrics": {"cow_criticals": 0, "cow_errors": 0, "cow_score": 0.33749522814096383, "cow_warnings": 2, "discussions": 2, "followers": 3, "issues": 0, "nb_hits": 0, "nb_uniq_visitors": 0, "nb_visits": 0, "reuses": 1, "views": 11}, "organization": {"acronym": null, "class": "Organization", "id": "534fff89a3a7292c64a77eb7", "logo": "https://next-static.data.gouv.fr/avatars/b2/0e83ec3699415a87640e97c51cb006-original.png", "logo_thumbnail": "https://next-static.data.gouv.fr/avatars/b2/0e83ec3699415a87640e97c51cb006-100.png", "name": "Mairie de Paris", "page": "https://next.data.gouv.fr/fr/organizations/mairie-de-paris/", "slug": "mairie-de-paris", "uri": "https://next.data.gouv.fr/api/1/organizations/mairie-de-paris/"}, "owner": null, "page": "https://next.data.gouv.fr/fr/datasets/les-titres-les-plus-pretes-dans-les-bibliotheques-de-pret-prs/", "private": null, "resources": [{"checksum": null, "created_at": "2014-07-13T13:21:31.795000", "description": "", "extras": {"check:available": true, "check:count-availability": 45, "check:date": "2019-06-12T10:26:24.717000", "check:status": 200, "check:url": "http://opendata.paris.fr/explore/dataset/les-titres-les-plus-pretes/download?format=csv"}, "filesize": null, "filetype": "remote", "format": "csv", "id": "fd394ae7-7d9a-45f5-ad12-2c9d08cbdf95", "last_modified": "2014-07-11T10:28:09.579000", "latest": "https://next.data.gouv.fr/fr/datasets/r/fd394ae7-7d9a-45f5-ad12-2c9d08cbdf95", "metrics": {"nb_hits": 0, "nb_uniq_visitors": 0, "nb_visits": 0, "views": 16}, "mime": null, "preview_url": null, "published": "2014-07-13T13:21:31.795000", "title": "Fichier CSV", "type": "main", "url": "http://opendata.paris.fr/explore/dataset/les-titres-les-plus-pretes/download?format=csv"}, {"checksum": null, "created_at": "2014-07-13T13:21:31.795000", "description": "", "extras": {"check:available": true, "check:count-availability": 21, "check:date": "2019-06-12T10:26:25.965000", "check:status": 200, "check:url": "http://opendata.paris.fr/explore/dataset/les-titres-les-plus-pretes/download?format=json"}, "filesize": null, "filetype": "remote", "format": "json", "id": "3816151b-a4c7-47ff-9273-91f96bf98711", "last_modified": "2014-07-11T10:28:09.579000", "latest": "https://next.data.gouv.fr/fr/datasets/r/3816151b-a4c7-47ff-9273-91f96bf98711", "metrics": {"nb_hits": 0, "nb_uniq_visitors": 0, "nb_visits": 0, "views": 4}, "mime": null, "preview_url": null, "published": "2014-07-13T13:21:31.795000", "title": "Fichier JSON", "type": "main", "url": "http://opendata.paris.fr/explore/dataset/les-titres-les-plus-pretes/download?format=json"}, {"checksum": null, "created_at": "2014-07-13T13:21:31.796000", "description": "", "extras": {"check:available": true, "check:count-availability": 45, "check:date": "2019-06-12T10:26:23.483000", "check:status": 200, "check:url": "http://opendata.paris.fr/explore/dataset/les-titres-les-plus-pretes/download?format=xls"}, "filesize": null, "filetype": "remote", "format": "xls", "id": "8a54c0da-be2f-40da-890d-842b0644def5", "last_modified": "2014-07-11T10:28:09.579000", "latest": "https://next.data.gouv.fr/fr/datasets/r/8a54c0da-be2f-40da-890d-842b0644def5", "metrics": {"nb_hits": 0, "nb_uniq_visitors": 0, "nb_visits": 0, "views": 22}, "mime": null, "preview_url": null, "published": "2014-07-13T13:21:31.796000", "title": "Fichier XLS", "type": "main", "url": "http://opendata.paris.fr/explore/dataset/les-titres-les-plus-pretes/download?format=xls"}, {"checksum": null, "created_at": "2014-07-13T13:21:31.796000", "description": "", "extras": {"check:available": false, "check:count-availability": 197, "check:date": "2019-06-12T10:26:25.969000", "check:status": 404, "check:url": "http://opendata.paris.fr/api/datasets/1.0/les-titres-les-plus-pretes/attachments/les_titres_les_plus_pretes_xls"}, "filesize": null, "filetype": "remote", "format": "xls", "id": "3ea54f05-5cff-4e96-a4d1-4a66d6af8000", "last_modified": "2014-07-11T10:28:09.579000", "latest": "https://next.data.gouv.fr/fr/datasets/r/3ea54f05-5cff-4e96-a4d1-4a66d6af8000", "metrics": {"nb_hits": 0, "nb_uniq_visitors": 0, "nb_visits": 0, "views": 24}, "mime": null, "preview_url": null, "published": "2014-07-13T13:21:31.796000", "title": "Les titres les plus prêtés.xls", "type": "main", "url": "http://opendata.paris.fr/api/datasets/1.0/les-titres-les-plus-pretes/attachments/les_titres_les_plus_pretes_xls"}], "slug": "les-titres-les-plus-pretes-dans-les-bibliotheques-de-pret-prs", "spatial": {"geom": null, "granularity": "other", "zones": ["fr:commune:75056@1943-01-01"]}, "tags": ["bibliotheques", "documents", "dvd", "livres", "pret", "references"], "temporal_coverage": null, "title": "Les titres les plus prêtés dans les bibliothèques de prêt", "uri": "https://next.data.gouv.fr/api/1/datasets/les-titres-les-plus-pretes-dans-les-bibliotheques-de-pret-prs/"}