{"acronym": null, "concat_title_org": null, "created_at": "Mon, 29 Nov 2021 19:02:40 GMT", "dataset_featured": 1, "dataset_followers": 1, "dataset_reuses": 0, "dataset_views": 1, "description": "Limites des cantons actuels, c'est à dire selon le [décret n° 2014-248 du 25 février 2014 portant délimitation des cantons dans le département des Pyrénées-Atlantiques](https://www.legifrance.gouv.fr/eli/decret/2014/2/25/INTA1401241D/jo), faisant suite à la [loi du 17 mai 2013](https://www.legifrance.gouv.fr/affichTexte.do?cidTexte=JORFTEXT000027414225&categorieLien=id).\n\n**Contexte de collecte**\n\nLes cantons ont été modifiés par le [décret n°2014-248 du 25 février 2014](https://www.legifrance.gouv.fr/eli/decret/2014/2/25/INTA1401241D/jo) portant délimitation des cantons dans le département des Pyrénées-Atlantiques, suite à la [loi du 17 mai 2013](https://www.legifrance.gouv.fr/affichTexte.do?cidTexte=JORFTEXT000027414225&categorieLien=id).\n\n**Méthode de collecte**\n\nLes cantons ont été dessinés sur la base du texte du décret en suivant les axes de voies. Bayonne est concerné par 3 cantons :\n\n* Le [canton n° 4 (Bayonne-1)](https://www.legifrance.gouv.fr/eli/decret/2014/2/25/2014-248/jo/article_5), qui comprend une partie d'Anglet et une partie de Bayonne\n* Le [canton n° 5 (Bayonne-2)](https://www.legifrance.gouv.fr/eli/decret/2014/2/25/2014-248/jo/article_6), qui comprend  la commune de Boucau et une partie de Bayonne\n* Le [canton n° 6 (Bayonne-3)](https://www.legifrance.gouv.fr/eli/decret/2014/2/25/2014-248/jo/article_7), qui comprend la partie de la commune de Bayonne non incluse dans les cantons de Bayonne-1 et de Bayonne-2\n\n**Attributs**\n\n| Champ | Alias | Type |\n| --- | --- | --- |\n| `NOM_PREFECTURE` | Nom préfecture | `varchar2` |\n| `NOM` | Nom | `varchar2` |\n| `NOM_BAYONNE` | Nom Bayonne | `varchar2` |\n| `CODE_INSEE` | Code INSEE | `number` |\n| `DECRET` | Décret | `varchar2` |\n| `GC_KEY` |  | `number` |\n\nPour plus d’informations, consultez [la métadonnée sur le catalogue Isogeo](https://open.isogeo.com/s/dfea79f9daa941fbb7fc9248309dc1c4/THU_tcV6SuOT_DsWqcQNzDenuhTV0/r/0b312281eee4463b9646050777fdc492).", "id": "61a515c084b460c93c4ed7a2", "orga_followers": 2, "orga_sp": 4, "organization": "Ville de Bayonne", "organization_id": "58d53c4688ee380aeea5e932", "organization_logo": "https://static.data.gouv.fr/avatars/0b/770fe445ca4f00984de7bbfe600baa-100.png", "resources_count": 1, "spatial_granularity": null, "spatial_zones": null, "temporal_coverage_end": null, "temporal_coverage_start": null, "title": "Contour des cantons - Bayonne", "url": "http://www.data.gouv.fr/fr/datasets/contour-des-cantons-bayonne-1/"}