{"acronym": null, "archived": null, "badges": [], "created_at": "2020-03-26T11:34:13.337000", "deleted": null, "description": "Prénoms des nouveaux-nés déclarés à l’état-civil à Antibes.", "extras": {}, "frequency": "annual", "frequency_date": "2022-01-31T00:00:00", "harvest": null, "id": "5e7c8525048a0a8a64d46188", "last_modified": "2022-01-31T11:48:35.400000", "last_update": "2022-01-31T11:48:35.400000", "license": "lov2", "metrics": {"discussions": 0, "followers": 0, "reuses": 0, "views": 1}, "organization": {"acronym": null, "badges": [{"kind": "public-service"}, {"kind": "certified"}], "class": "Organization", "id": "566594f388ee38738640355c", "logo": "https://demo-static.data.gouv.fr/avatars/c8/533a5ea1e8440097785a6324644503-original.png", "logo_thumbnail": "https://demo-static.data.gouv.fr/avatars/c8/533a5ea1e8440097785a6324644503-100.png", "name": "Ville d'Antibes", "page": "https://demo.data.gouv.fr/fr/organizations/ville-dantibes/", "slug": "ville-dantibes", "uri": "https://demo.data.gouv.fr/api/1/organizations/ville-dantibes/"}, "owner": null, "page": "https://demo.data.gouv.fr/fr/datasets/prenoms-des-nouveaux-nes-a-antibes/", "private": false, "quality": {"all_resources_available": true, "dataset_description_quality": false, "has_open_format": true, "has_resources": true, "license": true, "resources_documentation": false, "score": 0.7777777777777778, "spatial": true, "temporal_coverage": true, "update_frequency": true, "update_fulfilled_in_time": true}, "resources": [{"checksum": {"type": "sha1", "value": "065d3ee427000d84982bc92b47e1b2e7142c1f67"}, "created_at": "2021-02-19T10:19:41.081000", "description": null, "extras": {}, "filesize": 235634, "filetype": "file", "format": "csv", "harvest": null, "id": "aa632930-3fd2-4980-a517-f6609833242d", "last_modified": "2022-01-31T11:48:35.400000", "latest": "https://demo.data.gouv.fr/fr/datasets/r/aa632930-3fd2-4980-a517-f6609833242d", "metrics": {"views": 1}, "mime": "text/csv", "preview_url": "/tabular/preview/?url=https%3A%2F%2Fstatic.data.gouv.fr%2Fresources%2Fprenoms-des-nouveaux-nes-a-antibes%2F20220131-114826%2Fantibes-prenoms-naissance.csv", "published": "2021-02-19T10:19:41", "schema": {"name": "scdl/prenoms"}, "title": "antibes-prenoms-naissance.csv", "type": "main", "url": "https://static.data.gouv.fr/resources/prenoms-des-nouveaux-nes-a-antibes/20220131-114826/antibes-prenoms-naissance.csv"}, {"checksum": {"type": "sha1", "value": "121a9bd12dfdbb4219beed628bd8283c4951d943"}, "created_at": "2021-02-19T10:19:30.056000", "description": null, "extras": {}, "filesize": 837120, "filetype": "file", "format": "xls", "harvest": null, "id": "c76fb5a5-5cd9-404b-85fd-bd3f68a5b310", "last_modified": "2022-01-31T11:48:19.252000", "latest": "https://demo.data.gouv.fr/fr/datasets/r/c76fb5a5-5cd9-404b-85fd-bd3f68a5b310", "metrics": {"views": 1}, "mime": "application/vnd.ms-excel", "preview_url": "/tabular/preview/?url=https%3A%2F%2Fstatic.data.gouv.fr%2Fresources%2Fprenoms-des-nouveaux-nes-a-antibes%2F20220131-114815%2Fantibes-prenoms-naissance.xls", "published": "2021-02-19T10:19:30", "schema": {"name": "scdl/prenoms"}, "title": "antibes-prenoms-naissance.xls", "type": "main", "url": "https://static.data.gouv.fr/resources/prenoms-des-nouveaux-nes-a-antibes/20220131-114815/antibes-prenoms-naissance.xls"}], "slug": "prenoms-des-nouveaux-nes-a-antibes", "spatial": {"geom": null, "granularity": "fr:commune", "zones": ["fr:commune:06004@1943-01-01"]}, "tags": ["etat-civil", "naissance", "prenom", "scdl-prenoms", "schema"], "temporal_coverage": {"end": "2021-12-31", "start": "2011-01-01"}, "title": "Prénoms des nouveaux-nés à Antibes", "uri": "https://demo.data.gouv.fr/api/1/datasets/prenoms-des-nouveaux-nes-a-antibes/"}