{"acronym": null, "archived": null, "badges": [], "created_at": "2022-08-08T20:21:51.383000", "deleted": null, "description": "Données enregistrées par le bureau de la sécurité routière qui précise notamment le type d'accidents (bicyclette, moto ou cyclomoteur, piéton, poids lourd, véhicule léger et autres) ayant eu lieu dans l'Orne en 2018.", "extras": {}, "frequency": "unknown", "frequency_date": null, "harvest": {"backend": "DCAT", "dct_identifier": "fr-120066022-jdd-aa972396-ada9-4471-953b-9bf6f5698587", "domain": "www.geocatalogue.fr", "last_update": "2022-12-02T05:28:49.621000", "remote_id": "fr-120066022-jdd-aa972396-ada9-4471-953b-9bf6f5698587", "remote_url": "https://data.geocatalogue.fr/id/dataset/fr-120066022-jdd-aa972396-ada9-4471-953b-9bf6f5698587", "source_id": "63652025e3b36380100e2d6d", "uri": "https://data.geocatalogue.fr/id/dataset/fr-120066022-jdd-aa972396-ada9-4471-953b-9bf6f5698587"}, "id": "62f1543fd0ce0dcce83e86c4", "last_modified": "2022-08-08T20:21:51.383000", "last_update": "2022-08-08T20:21:51.385000", "license": "notspecified", "metrics": {"discussions": 0, "followers": 0, "reuses": 0, "views": 0}, "organization": {"acronym": "DDT 61", "badges": [], "class": "Organization", "id": "558e9b15c751df2a26a453b9", "logo": "https://demo-static.data.gouv.fr/avatars/2015-06-27/4c40e3c6faf843de873b747aa4615244/logo_DDT-original.png", "logo_thumbnail": "https://demo-static.data.gouv.fr/avatars/2015-06-27/4c40e3c6faf843de873b747aa4615244/logo_DDT-100.png", "name": "Direction Départementale des Territoires de l'Orne", "page": "https://demo.data.gouv.fr/fr/organizations/direction-departementale-des-territoires-de-lorne/", "slug": "direction-departementale-des-territoires-de-lorne", "uri": "https://demo.data.gouv.fr/api/1/organizations/direction-departementale-des-territoires-de-lorne/"}, "owner": null, "page": "https://demo.data.gouv.fr/fr/datasets/les-accidents-corporels-de-la-route-dans-lorne-en-2018/", "private": false, "quality": {"all_resources_available": true, "dataset_description_quality": true, "has_open_format": false, "has_resources": true, "license": true, "resources_documentation": true, "score": 0.4444444444444444, "spatial": false, "temporal_coverage": false, "update_frequency": null}, "resources": [{"checksum": null, "created_at": "2022-08-08T20:21:51.384000", "description": "Vue XML des métadonnées", "extras": {}, "filesize": null, "filetype": "file", "format": null, "harvest": {"uri": "fr-120066022-jdd-aa972396-ada9-4471-953b-9bf6f5698587/#resource-c5ad4c38-5ea7-11ed-a223-7c70db03839b"}, "id": "d73306f2-8c8b-4379-bd43-8a32d7b4f4e8", "last_modified": "2022-08-08T20:21:51.384000", "latest": "https://demo.data.gouv.fr/fr/datasets/r/d73306f2-8c8b-4379-bd43-8a32d7b4f4e8", "metrics": {}, "mime": null, "preview_url": null, "published": "2022-08-08T20:21:51.384000", "schema": {}, "title": "Ressource sans nom", "type": "main", "url": "https://ogc.geo-ide.developpement-durable.gouv.fr/csw/all-dataset?REQUEST=GetRecordById&SERVICE=CSW&VERSION=2.0.2&RESULTTYPE=results&elementSetName=full&TYPENAMES=gmd:MD_Metadata&OUTPUTSCHEMA=http://www.isotc211.org/2005/gmd&ID=fr-120066022-jdd-aa972396-ada9-4471-953b-9bf6f5698587"}, {"checksum": null, "created_at": "2022-08-08T20:21:51.385000", "description": "Vue HTML des métadonnées sur internet", "extras": {}, "filesize": null, "filetype": "file", "format": null, "harvest": {"uri": "fr-120066022-jdd-aa972396-ada9-4471-953b-9bf6f5698587/#resource-c5ad4c37-5ea7-11ed-ab1e-7c70db03839b"}, "id": "1fc03371-a71d-4c93-8b8c-4089b25cebfb", "last_modified": "2022-08-08T20:21:51.385000", "latest": "https://demo.data.gouv.fr/fr/datasets/r/1fc03371-a71d-4c93-8b8c-4089b25cebfb", "metrics": {}, "mime": null, "preview_url": null, "published": "2022-08-08T20:21:51.385000", "schema": {}, "title": "Ressource sans nom", "type": "main", "url": "http://catalogue.geo-ide.developpement-durable.gouv.fr/catalogue/srv/fre/catalog.search#/metadata/fr-120066022-jdd-aa972396-ada9-4471-953b-9bf6f5698587"}], "slug": "les-accidents-corporels-de-la-route-dans-lorne-en-2018", "spatial": null, "tags": ["accidents", "donnees-ouvertes", "transports-deplacements-securite-routiere"], "temporal_coverage": null, "title": "Les accidents corporels de la route dans l'Orne en 2018.", "uri": "https://demo.data.gouv.fr/api/1/datasets/les-accidents-corporels-de-la-route-dans-lorne-en-2018/"}