{"badges": [], "created_at": "2015-06-10T16:16:30.923000", "datasets": [{"page": "https://www.data.gouv.fr/fr/datasets/base-permanente-des-equipements-1/", "title": "Base permanente des équipements", "uri": "https://www.data.gouv.fr/api/1/datasets/base-permanente-des-equipements-1/"}], "deleted": null, "description": "L'état offre des logements sociaux pouvant être meublés selon les régions mais des disparités subsistent.", "featured": null, "id": "557846bec751df4e24e5726b", "image": null, "image_thumbnail": null, "last_modified": "2021-08-04T12:24:00.141000", "metrics": {"datasets": 1, "discussions": 0, "followers": 0, "views": 0}, "organization": null, "owner": {"avatar": null, "avatar_thumbnail": null, "class": "User", "first_name": "arnaud", "id": "557844fec751df5f3de5726a", "last_name": "valogne", "page": "https://www.data.gouv.fr/fr/users/arnaud-valogne/", "slug": "arnaud-valogne", "uri": "https://www.data.gouv.fr/api/1/users/arnaud-valogne/"}, "page": "https://www.data.gouv.fr/fr/reuses/cartographie-logements-sociaux-meubles/", "private": false, "slug": "cartographie-logements-sociaux-meubles", "tags": [], "title": "Cartographie logements sociaux meublés", "type": "api", "uri": "https://www.data.gouv.fr/api/1/reuses/cartographie-logements-sociaux-meubles/", "url": "http://www.semeubler.com/"}