{"badges": [], "created_at": "2019-05-01T09:19:57.693000", "datasets": [{"page": "https://www.data.gouv.fr/fr/datasets/demandes-de-valeurs-foncieres-geolocalisees/", "title": "Demandes de valeurs foncières géolocalisées", "uri": "https://www.data.gouv.fr/api/1/datasets/demandes-de-valeurs-foncieres-geolocalisees/"}], "deleted": null, "description": "Cette carte présente une visualisation en 3D du prix moyen au m2 pour les appartements de Rennes. Pour chaque parcelle, sa hauteur correspond au prix moyen de toutes les transactions qui ont eu lieu entre 2014 et 2018.\n\nNous avons aussi agrégé les transactions de chaque parcelle en fonction du nombre de pièces principales des appartements. La hauteur de la couleur est proportionnelle au pourcentage de transactions pour chaque valeur du nombre de pièces.", "featured": true, "id": "5cc9489d634f410272858a47", "image": "https://static.data.gouv.fr/images/45/ed78acfa0b4ba2aa5c69a2e5d8ba58.png", "image_thumbnail": "https://static.data.gouv.fr/images/45/ed78acfa0b4ba2aa5c69a2e5d8ba58-500.png", "last_modified": "2021-12-24T19:59:26.809000", "metrics": {"datasets": 1, "discussions": 0, "followers": 1, "views": 986}, "organization": {"acronym": null, "badges": [], "class": "Organization", "id": "589596c188ee3877169b81a4", "logo": "https://static.data.gouv.fr/avatars/92/e55448f2ae493dbd1395ae6096a5f2-original.png", "logo_thumbnail": "https://static.data.gouv.fr/avatars/92/e55448f2ae493dbd1395ae6096a5f2-100.png", "name": "Koumoul", "page": "https://www.data.gouv.fr/fr/organizations/koumoul-1/", "slug": "koumoul-1", "uri": "https://www.data.gouv.fr/api/1/organizations/koumoul-1/"}, "owner": null, "page": "https://www.data.gouv.fr/fr/reuses/dvf-pour-les-appartements-de-rennes/", "private": false, "slug": "dvf-pour-les-appartements-de-rennes", "tags": ["carte", "dvf", "immobilier", "visualisation"], "title": "DVF pour les appartements de Rennes", "type": "visualization", "uri": "https://www.data.gouv.fr/api/1/reuses/dvf-pour-les-appartements-de-rennes/", "url": "https://opendata.koumoul.com/reuses/dvf-appartements-rennes"}