{"created_at": "Fri, 28 Jun 2019 13:42:12 GMT", "description": "lecadastre.com est un site qui permet aux utilisateurs de consulter le cadastre de leur ville simplement et rapidement. Le site présente l'ensemble des feuilles cadastrales disponibles pour la France. L'utilisateur peut rechercher une parcelle par numéro ou par adresse postale. La recherche se fait ville par ville (le tuillage n'a pas été fait au niveau national). \nLes valeurs foncières ont été transformées en transactions immobilières pour avoir une vision marché immobilier au niveau local.\nLes données de l'annuaire de l'administration permettent une mise en relation avec les administrations compétentes en fonction des besoins.", "id": "5d1651746f44414d14973df2", "orga_followers": null, "organization": null, "organization_id": null, "reuse_datasets": 4, "reuse_featured": 1, "reuse_followers": 1, "reuse_views": 4, "title": "lecadastre.com", "url": "http://www.data.gouv.fr/fr/reuses/lecadastre-com/"}