{"created_at": "Fri, 17 Apr 2020 14:11:42 GMT", "description": "Le croisement de 3 modèles a permis de simuler la propagation du CoViD-19, habitant par habitant, dans toute la France. L'objectif est de pouvoir simuler l'impact de différents scénarios de dé-confinement sur l'impact de l'épidémie sur la population, avec une granularité géographique à l'échelle des bâtiments, et des tranches d'âge par intervalle de 10 ans.\n- un premier modèle utilise les données opendata pour la répartition des habitants, bâtiment par bâtiment\n- un second modèle permet de simuler le déplacement de chaque personne\n- un troisième modèle d'épidémiologie permet de simuler la propagation du virus entre chaque individu, jour après jour.\n\nToutes les infos et résultats : http://www.epidemap.com\nQuelques vidéos montrant la propagation de l’épidémie habitant par habitant, bâtiment par bâtiment, sur toute la France, l’impact d’un potentiel dé confinement brutal, etc. :\nhttps://www.youtube.com/watch?v=y2CJZiHy6TA\nhttps://www.youtube.com/watch?v=Hx8vB6BAWUk\nhttps://www.youtube.com/watch?v=V1iUhQukxmo", "id": "5e999cfe4662724718caa71c", "orga_followers": 2, "organization": "Epidemap", "organization_id": "5e999b44bdbee9a691fc51a8", "reuse_datasets": 1, "reuse_featured": 1, "reuse_followers": 1, "reuse_views": 4, "title": "Modélisation de l'évolution des épidémies (CoViD-19)", "url": "http://www.data.gouv.fr/fr/reuses/modelisation-de-levolution-des-epidemies-covid-19/"}